starlette_sessions/__init__.py
starlette_sessions/backend.py
starlette_sessions/base.py
starlette_sessions/constants.py
starlette_sessions/cookie/__init__.py
starlette_sessions/cookie/backend.py
starlette_sessions/cookie/base.py
starlette_sessions/memory/__init__.py
starlette_sessions/memory/backend.py
starlette_sessions/middleware.py
starlette_sessions/py.typed
starlette_sessions/redis/__init__.py
starlette_sessions/redis/backend.py
starlette_sessions/signedcookie/__init__.py
starlette_sessions/signedcookie/backend.py
starlette_sessions-0.3.0.dist-info/LICENSE
starlette_sessions-0.3.0.dist-info/METADATA
starlette_sessions-0.3.0.dist-info/WHEEL
starlette_sessions-0.3.0.dist-info/RECORD
