Metadata-Version: 2.1
Name: starlette-sessions
Version: 0.3.0
Summary: Adds server-side session support to your Starlette application
Author: Jesse McLaughlin
Author-email: nzjess@gmail.com
Requires-Python: >=3.8
Classifier: Programming Language :: Python :: 3
Classifier: Programming Language :: Python :: 3.8
Classifier: Programming Language :: Python :: 3.9
Classifier: Programming Language :: Python :: 3.10
Classifier: Programming Language :: Python :: 3.11
Classifier: Programming Language :: Python :: 3.12
Provides-Extra: redis
Provides-Extra: securecookie
Requires-Dist: itsdangerous (>=2,<3) ; extra == "securecookie"
Requires-Dist: redis (>=4) ; extra == "redis"
Requires-Dist: starlette (>=0.40.0)
